odoo/addons/ssi_accountant_general_audit_ws_ra230/README.rst
odoo/addons/ssi_accountant_general_audit_ws_ra230/__init__.py
odoo/addons/ssi_accountant_general_audit_ws_ra230/__manifest__.py
odoo/addons/ssi_accountant_general_audit_ws_ra230/data/accountant_general_audit_worksheet_conclusion_data.xml
odoo/addons/ssi_accountant_general_audit_ws_ra230/data/accountant_general_audit_worksheet_type_data.xml
odoo/addons/ssi_accountant_general_audit_ws_ra230/data/approval_template_data.xml
odoo/addons/ssi_accountant_general_audit_ws_ra230/data/ir_sequence_data.xml
odoo/addons/ssi_accountant_general_audit_ws_ra230/data/policy_template_data.xml
odoo/addons/ssi_accountant_general_audit_ws_ra230/data/sequence_template_data.xml
odoo/addons/ssi_accountant_general_audit_ws_ra230/models/__init__.py
odoo/addons/ssi_accountant_general_audit_ws_ra230/models/accountant_general_audit_standard_detail.py
odoo/addons/ssi_accountant_general_audit_ws_ra230/models/ws_ra230.py
odoo/addons/ssi_accountant_general_audit_ws_ra230/models/ws_ra230_account_assersion_level_romm.py
odoo/addons/ssi_accountant_general_audit_ws_ra230/security/ir.model.access.csv
odoo/addons/ssi_accountant_general_audit_ws_ra230/security/ir_module_category_data.xml
odoo/addons/ssi_accountant_general_audit_ws_ra230/security/ir_rule_data.xml
odoo/addons/ssi_accountant_general_audit_ws_ra230/security/res_group_data.xml
odoo/addons/ssi_accountant_general_audit_ws_ra230/static/description/icon.png
odoo/addons/ssi_accountant_general_audit_ws_ra230/views/accountant_general_audit_standard_detail_views.xml
odoo/addons/ssi_accountant_general_audit_ws_ra230/views/ws_ra230_views.xml
odoo14_addon_ssi_accountant_general_audit_ws_ra230-14.0.1.0.2.dev1.dist-info/METADATA
odoo14_addon_ssi_accountant_general_audit_ws_ra230-14.0.1.0.2.dev1.dist-info/WHEEL
odoo14_addon_ssi_accountant_general_audit_ws_ra230-14.0.1.0.2.dev1.dist-info/top_level.txt
odoo14_addon_ssi_accountant_general_audit_ws_ra230-14.0.1.0.2.dev1.dist-info/RECORD
